{"version": "1", "message": "ERROR: Hidden Testcases server unreachable.", "problem_id": "ads2_m7_a1_1", "user_id": "madhavimvh", "score": {"sample": {"0": {"execution_time": 0.7291336059570312, "passed": true}, "1": {"execution_time": 0.22641944885253906, "passed": true}, "2": {"execution_time": 0.2723114490509033, "passed": true}, "3": {"execution_time": 0.2074441909790039, "passed": true}, "4": {"execution_time": 0.19959568977355957, "passed": true}, "5": {"execution_time": 0.19946622848510742, "passed": true}}}, "check_style_score": "0/1"}